fuzzy_control/__init__.py
fuzzy_control-0.0.0.dist-info/METADATA
fuzzy_control-0.0.0.dist-info/WHEEL
fuzzy_control-0.0.0.dist-info/RECORD
