Metadata-Version: 2.3
Name: fuzzy-control
Version: 0.0.0
Summary: Coming soon.
Author-email: John Wesley Hostetter <jhostetter16@gmail.com>
